{
  "events": [
    {
      "category": "邂逅",
      "chapter": "3",
      "characters": "李青鸾,萧逸辰",
      "content": "秘密花园的初遇",
      "end": "1111-04-27",
      "group": "主角团",
      "id": 1682471900001,
      "keyCharacter": "",
      "key_character": "李青鸾",
      "location": "皇宫后花园",
      "note": "",
      "season": "春季",
      "specialDay": "",
      "special_day": "上巳节",
      "start": "1111-04-23",
      "story": "李青鸾在皇宫后花园邂逅神秘少年萧逸辰，因一本古籍结缘。\n",
      "tags": "",
      "title": "秘密花园的初遇",
      "url": "/static/novel/jpm/text/part0004.html#p001",
      "weather": "细雨蒙蒙"
    },
    {
      "category": "阴谋",
      "chapter": "4",
      "characters": "曹玉,白无常",
      "content": "密谋政变",
      "end": null,
      "group": "反派势力",
      "id": 1682471900002,
      "keyCharacter": "",
      "key_character": "曹玉",
      "location": "东厂密室",
      "note": "",
      "season": "春季",
      "specialDay": "",
      "special_day": "",
      "start": "1111-04-25",
      "story": "曹玉与白无常在密室中策划颠覆皇权，暗中布置刺杀计划。",
      "tags": "",
      "title": "密谋政变",
      "url": "/static/novel/jpm/text/part0000.html",
      "weather": "阴"
    },
    {
      "category": "修炼",
      "chapter": "5",
      "characters": "萧逸辰",
      "content": "月下练剑",
      "group": "主角团",
      "id": 1682471900003,
      "keyCharacter": "",
      "key_character": "萧逸辰",
      "location": "梅花林",
      "note": "",
      "season": "春季",
      "specialDay": "",
      "special_day": "",
      "start": "1111-04-27",
      "story": "萧逸辰在梅花林月夜独自练剑，回忆起年少丧母之痛。",
      "tags": "",
      "title": "月下练剑",
      "url": "/static/novel/jpm/text/part0004.html#p000",
      "weather": "晴",
      "end": null
    },
    {
      "category": "武斗",
      "chapter": "6",
      "characters": "秦烟儿,各大江湖俊杰",
      "content": "比武招亲",
      "group": "江湖门派",
      "id": 1682471900004,
      "keyCharacter": "",
      "key_character": "秦烟儿",
      "location": "天香楼",
      "note": "",
      "season": "夏季",
      "specialDay": "中秋节",
      "special_day": "",
      "start": "1111-05-02",
      "story": "秦烟儿主办比武招亲，\n\n\n众多江湖俊杰前来挑战。",
      "tags": "战斗,江湖",
      "title": "比武招亲",
      "weather": "炎热",
      "end": null
    },
    {
      "category": "死亡",
      "chapter": "7",
      "characters": "赵守义",
      "content": "毒发身亡",
      "end": null,
      "group": "主角团",
      "id": 1682471900005,
      "keyCharacter": "老挝",
      "key_character": "赵守义",
      "location": "医馆",
      "note": "",
      "season": "夏季",
      "specialDay": "元旦节",
      "special_day": "端午节",
      "start": "1111-05-05",
      "story": "赵守义因服毒太晚，临终前托付青鸾调查真相。",
      "tags": "",
      "title": "毒发身亡",
      "weather": "闷热"
    }
  ]
}